imgw_pib/__init__.py
imgw_pib/const.py
imgw_pib/exceptions.py
imgw_pib/model.py
imgw_pib/py.typed
imgw_pib/utils.py
imgw_pib/data/rivers.json
imgw_pib/data/weather_stations_info.json
imgw_pib-2.0.1.dist-info/licenses/LICENSE
imgw_pib-2.0.1.dist-info/METADATA
imgw_pib-2.0.1.dist-info/WHEEL
imgw_pib-2.0.1.dist-info/top_level.txt
imgw_pib-2.0.1.dist-info/RECORD
