Metadata-Version: 2.4
Name: imgw_pib
Version: 2.0.1
Summary: Python wrapper for IMGW-PIB API.
Author: Maciej Bieniek
License-Expression: Apache-2.0
Project-URL: Homepage, https://github.com/bieniu/imgw-pib
Classifier: Development Status :: 5 - Production/Stable
Classifier: Operating System :: OS Independent
Classifier: Programming Language :: Python
Classifier: Programming Language :: Python :: 3
Classifier: Programming Language :: Python :: 3.13
Classifier: Programming Language :: Python :: 3.14
Classifier: Programming Language :: Python :: 3 :: Only
Classifier: Typing :: Typed
Requires-Python: >=3.13
License-File: LICENSE
Requires-Dist: aiofiles
Requires-Dist: aiohttp>=3.9.4
Requires-Dist: orjson
Requires-Dist: yarl
Dynamic: license-file
